preprocess_corpora/__init__.py
preprocess_corpora/alignment/__init__.py
preprocess_corpora/alignment/align.py
preprocess_corpora/alignment/merge_alignments.py
preprocess_corpora/core/__init__.py
preprocess_corpora/core/constants.py
preprocess_corpora/preprocessing/__init__.py
preprocess_corpora/preprocessing/preprocess.py
preprocess_corpora/preprocessing/process.py
preprocess_corpora/preprocessing/tag.py
preprocess_corpora/preprocessing/tok.py
preprocess_corpora/tests/__init__.py
preprocess_corpora/tests/test_align.py
preprocess_corpora/tests/test_process.py
preprocess_corpora-0.1.1.dist-info/LICENSE
preprocess_corpora-0.1.1.dist-info/METADATA
preprocess_corpora-0.1.1.dist-info/WHEEL
preprocess_corpora-0.1.1.dist-info/entry_points.txt
preprocess_corpora-0.1.1.dist-info/top_level.txt
preprocess_corpora-0.1.1.dist-info/RECORD
