Metadata-Version: 2.1
Name: preprocess-corpora
Version: 0.1.1
Summary: Preprocessing and sentence-aligning for parallel corpora
Home-page: https://github.com/time-in-translation/preprocess-corpora
Author: Martijn van der Klis
Author-email: m.h.vanderklis@uu.nl
License: MIT
Platform: UNKNOWN
Classifier: Development Status :: 4 - Beta
Classifier: License :: OSI Approved :: MIT License
Classifier: Programming Language :: Python :: 3
Classifier: Operating System :: POSIX :: Linux
Classifier: Topic :: Text Processing :: Linguistic
Requires-Python: >=3.5
Requires-Dist: click
Requires-Dist: python-docx
Requires-Dist: treetagger-xml
